LICENSE
MANIFEST.in
README.md
setup.cfg
setup.py
comment_parser/__init__.py
comment_parser/comment_parser.py
comment_parser.egg-info/PKG-INFO
comment_parser.egg-info/SOURCES.txt
comment_parser.egg-info/dependency_links.txt
comment_parser.egg-info/not-zip-safe
comment_parser.egg-info/requires.txt
comment_parser.egg-info/top_level.txt
comment_parser/parsers/__init__.py
comment_parser/parsers/c_parser.py
comment_parser/parsers/common.py
comment_parser/parsers/go_parser.py
comment_parser/parsers/html_parser.py
comment_parser/parsers/js_parser.py
comment_parser/parsers/python_parser.py
comment_parser/parsers/ruby_parser.py
comment_parser/parsers/shell_parser.py