Metadata-Version: 2.1
Name: comment-parser
Version: 1.2.5
Summary: Parse comments from various source files.
Home-page: http://github.com/jeanralphaviles/comment_parser
Author: Jean-Ralph Aviles
Author-email: jeanralph.aviles+pypi@gmail.com
License: MIT
Platform: UNKNOWN
Classifier: Development Status :: 5 - Production/Stable
Classifier: Programming Language :: Python :: 3
Classifier: Topic :: Software Development :: Documentation
Classifier: License :: OSI Approved :: MIT License
Requires-Python: >=3.13
License-File: LICENSE
